LICENCE.txt
MANIFEST.in
README.md
evaluate.py
inference.py
load.py
preprocess.py
setup.py
train.py
dsp_house_prices.egg-info/PKG-INFO
dsp_house_prices.egg-info/SOURCES.txt
dsp_house_prices.egg-info/dependency_links.txt
dsp_house_prices.egg-info/top_level.txt